README.md
pyproject.toml
setup.cfg
setup.py
openapi_client/__init__.py
openapi_client/api_client.py
openapi_client/api_response.py
openapi_client/configuration.py
openapi_client/exceptions.py
openapi_client/py.typed
openapi_client/rest.py
openapi_client/api/__init__.py
openapi_client/api/default_api.py
openapi_client/models/__init__.py
openapi_client/models/api_query_get200_response_inner.py
openapi_client/models/get200_response_inner.py
sage_ai_my_for.egg-info/PKG-INFO
sage_ai_my_for.egg-info/SOURCES.txt
sage_ai_my_for.egg-info/dependency_links.txt
sage_ai_my_for.egg-info/requires.txt
sage_ai_my_for.egg-info/top_level.txt
test/test_api_query_get200_response_inner.py
test/test_default_api.py
test/test_get200_response_inner.py